{"name":"Yas","type":"Motor Yacht","yac_model":"Custom","sub_type":"","builder":"ADMShipyards","naval_architect":"AITAC Koninklijke Schelde Groep BV (KSG)","exterior_designers":"Pierrejean Design Studio","interior_designer":"Pierrejean Design Studio","year":"2011","flag":"","mca":"Yes","class_":"","hull_nb":"","hull_colour":"","length_overall":"141.00m (462'7\"ft)","length_at_waterline":"132.00m (433'0\"ft)","beam":"15.00m (49'2\"ft)","draft_min":"4.20m (13'9\"ft)","draft_max":"4.30m (14'1\"ft)","gross_tonnage":"","guests":"60","cabins_total":"","cabins":"","crew":"56","hull_configuration":"","hull_material":"Steel","superstructure":"GRP","deck_material":"","decks_nb":"","quantity":"2","fuel_type":"Diesel","manufacturer":"MTU","eng_model":"","power":"10500hp / 7830kW","total_power":"21000hp / 15660kW","propulsion":"Twin Screw","max_speed":"26.00 kts","cruising_speed":"23.00 kts","range":"","fuel_capacity":"","water_capacity":"","generator":"","stabilizers":"","thrusters":"","amenities":""}
{"name":"Ocean Victory","type":"Motor Yacht","yac_model":"Custom","sub_type":"","builder":"Fincantieri Yachts","naval_architect":"Espen Oeino","exterior_designers":"Espen Oeino","interior_designer":"Alberto Pinto Studio Laura Sessa","year":"2014","flag":"Cayman Islands","mca":"","class_":"SOLAS","hull_nb":"6218","hull_colour":"","length_overall":"140.00m (459'3\"ft)","length_at_waterline":"","beam":"","draft_min":"","draft_max":"","gross_tonnage":"","guests":"","cabins_total":"","cabins":"","crew":"","hull_configuration":"Displacement","hull_material":"Steel","superstructure":"Aluminium","deck_material":"","decks_nb":"","quantity":"2","fuel_type":"Diesel","manufacturer":"MTU","eng_model":"","power":"10500hp / 7830kW","total_power":"- / -","propulsion":"","max_speed":"0.00 kts","cruising_speed":"0.00 kts","range":"","fuel_capacity":"","water_capacity":"","generator":"","stabilizers":"","thrusters":"","amenities":""}
{"name":"Eclipse","type":"Motor Yacht","yac_model":"Custom","sub_type":"","builder":"Blohm + Voss Shipyards","naval_architect":"Blohm + Voss Shipyards","exterior_designers":"Terence Disdale","interior_designer":"Terence Disdale","year":"2010","flag":"Bermuda","mca":"","class_":"Lloyds Register","hull_nb":"978","hull_colour":"","length_overall":"162.50m (533'1\"ft)","length_at_waterline":"","beam":"22.00m (72'2\"ft)","draft_min":"","draft_max":"5.90m (19'4\"ft)","gross_tonnage":"13000 tonnes","guests":"36","cabins_total":"18","cabins":"1 Master / 17 VIP /","crew":"70","hull_configuration":"Displacement","hull_material":"Steel","superstructure":"Aluminium","deck_material":"","decks_nb":"","quantity":"4","fuel_type":"Diesel","manufacturer":"","eng_model":"20V 1163 TB93","power":"- / -","total_power":"- / -","propulsion":"Triple Screw","max_speed":"25.00 kts","cruising_speed":"22.00 kts","range":"","fuel_capacity":"","water_capacity":"","generator":"","stabilizers":"","thrusters":"","amenities":""}
{"name":"Dubai","type":"Motor Yacht","yac_model":"Custom","sub_type":"","builder":"Platinum Yachts","naval_architect":"Blohm + Voss Shipyards","exterior_designers":"Winch Design","interior_designer":"Platinum Yachts","year":"2006 / 2008","flag":"UEA","mca":"Yes","class_":"LR","hull_nb":"965","hull_colour":"","length_overall":"162.00m (531'5\"ft)","length_at_waterline":"","beam":"22.40m (73'5\"ft)","draft_min":"","draft_max":"5.00m (16'4\"ft)","gross_tonnage":"12488 tonnes","guests":"72","cabins_total":"44","cabins":"","crew":"88","hull_configuration":"","hull_material":"Steel","superstructure":"Steel / Aluminium","deck_material":"Teak","decks_nb":"","quantity":"4","fuel_type":"Diesel","manufacturer":"","eng_model":"20V 1163 TB93","power":"9625hp / 7177kW","total_power":"38500hp / 28708kW","propulsion":"Twin Screw","max_speed":"26.00 kts","cruising_speed":"25.00 kts","range":"8500.00 miles at 25 kts","fuel_capacity":"","water_capacity":"","generator":"","stabilizers":"","thrusters":"","amenities":""}
{"name":"Flying Fox","type":"Motor Yacht","yac_model":"Custom","sub_type":"","builder":"Lurssen Yachts","naval_architect":"Lurssen Yachts","exterior_designers":"Espen Oeino","interior_designer":"Mark Berryman","year":"2018","flag":"","mca":"","class_":"","hull_nb":"","hull_colour":"","length_overall":"136.00m (446'2\"ft)","length_at_waterline":"","beam":"20.50m (67'3\"ft)","draft_min":"","draft_max":"","gross_tonnage":"","guests":"","cabins_total":"","cabins":"","crew":"","hull_configuration":"Displacement","hull_material":"Steel","superstructure":"Aluminium","deck_material":"","decks_nb":"5","quantity":"4","fuel_type":"Diesel","manufacturer":"","eng_model":"20V 1163 TB93","power":"9625hp / 7177kW","total_power":"- / -","propulsion":"","max_speed":"","cruising_speed":"","range":"","fuel_capacity":"","water_capacity":"","generator":"- - -","stabilizers":"","thrusters":"","amenities":""}
{"name":"Maryah","type":"Motor Yacht","yac_model":"Custom","sub_type":"","builder":"Neorion Elefsis Shipyards","naval_architect":"Naos","exterior_designers":"H2 Yacht Design","interior_designer":"H2 Yacht Design","year":"2014","flag":"Greece","mca":"","class_":"Lloyds Register / SOLAS","hull_nb":"","hull_colour":"","length_overall":"125.00m (410'1\"ft)","length_at_waterline":"","beam":"17.00m (55'9\"ft)","draft_min":"","draft_max":"5.60m (18'4\"ft)","gross_tonnage":"5650 tonnes","guests":"","cabins_total":"","cabins":"","crew":"","hull_configuration":"","hull_material":"Steel","superstructure":"Aluminium","deck_material":"","decks_nb":"6","quantity":"5","fuel_type":"Diesel-Electric","manufacturer":"Caterpillar","eng_model":"","power":"2146hp / 1600kW","total_power":"10730hp / 8000kW","propulsion":"Twin Azipods","max_speed":"18.00 kts","cruising_speed":"","range":"","fuel_capacity":"533,000.00 L / 117,243.48 USG","water_capacity":"216,000.00 L / 47,513.30 USG","generator":"","stabilizers":"","thrusters":"","amenities":""}
{"name":"Al Said","type":"Motor Yacht","yac_model":"Custom","sub_type":"","builder":"Lurssen Yachts","naval_architect":"Lurssen Yachts","exterior_designers":"Espen Oeino","interior_designer":"RWD","year":"2008","flag":"Oman","mca":"","class_":"GL","hull_nb":"13644","hull_colour":"","length_overall":"155.00m (508'6\"ft)","length_at_waterline":"","beam":"24.00m (78'8\"ft)","draft_min":"","draft_max":"5.20m (17'0\"ft)","gross_tonnage":"","guests":"70","cabins_total":"","cabins":"","crew":"154","hull_configuration":"","hull_material":"Steel","superstructure":"Aluminium","deck_material":"","decks_nb":"","quantity":"2","fuel_type":"","manufacturer":"","eng_model":"","power":"10996hp / 8200kW","total_power":"21992hp / 16400kW","propulsion":"","max_speed":"25.00 kts","cruising_speed":"22.00 kts","range":"","fuel_capacity":"","water_capacity":"","generator":"","stabilizers":"","thrusters":"","amenities":""}
{"name":"Crescent","type":"Motor Yacht","yac_model":"Custom","sub_type":"","builder":"Lurssen Yachts","naval_architect":"Lurssen Yachts","exterior_designers":"Espen Oeino","interior_designer":"","year":"2017","flag":"","mca":"","class_":"","hull_nb":"","hull_colour":"","length_overall":"135.00m (442'10\"ft)","length_at_waterline":"","beam":"22.00m (72'2\"ft)","draft_min":"","draft_max":"","gross_tonnage":"","guests":"","cabins_total":"","cabins":"","crew":"","hull_configuration":"Displacement","hull_material":"Steel","superstructure":"Aluminium","deck_material":"","decks_nb":"4","quantity":"2","fuel_type":"","manufacturer":"","eng_model":"","power":"10996hp / 8200kW","total_power":"- / -","propulsion":"","max_speed":"","cruising_speed":"","range":"","fuel_capacity":"","water_capacity":"","generator":"","stabilizers":"","thrusters":"","amenities":""}
{"name":"Octopus","type":"Motor Yacht","yac_model":"Custom","sub_type":"","builder":"Lurssen Yachts","naval_architect":"Lurssen Yachts","exterior_designers":"Espen Oeino","interior_designer":"Jonathan Quinn Barnett","year":"2003 / 2008","flag":"Cayman Islands","mca":"Yes","class_":"LR","hull_nb":"13622","hull_colour":"","length_overall":"126.20m (414'0\"ft)","length_at_waterline":"109.95m (360'8\"ft)","beam":"21.00m (68'10\"ft)","draft_min":"","draft_max":"5.66m (18'6\"ft)","gross_tonnage":"","guests":"26","cabins_total":"41","cabins":"","crew":"57","hull_configuration":"","hull_material":"Steel","superstructure":"Aluminium","deck_material":"Teak","decks_nb":"","quantity":"8","fuel_type":"Diesel","manufacturer":"Mercedes","eng_model":"","power":"2400hp / 1790kW","total_power":"19200hp / 14320kW","propulsion":"Twin Screw","max_speed":"20.00 kts","cruising_speed":"17.00 kts","range":"","fuel_capacity":"850,000.00 L / 186,973.65 USG","water_capacity":"175,000.00 L / 38,494.58 USG","generator":"","stabilizers":"","thrusters":"","amenities":""}
{"name":"El Mahrousa","type":"Motor Yacht","yac_model":"Custom","sub_type":"","builder":"Samuda Bros.","naval_architect":"Sir Oliver Lang","exterior_designers":"Sir Oliver Lang","interior_designer":"","year":"1865 / 1987","flag":"Egipt","mca":"","class_":"LR","hull_nb":"","hull_colour":"","length_overall":"145.72m (478'1\"ft)","length_at_waterline":"","beam":"13.00m (42'7\"ft)","draft_min":"","draft_max":"5.30m (17'4\"ft)","gross_tonnage":"4561 tonnes","guests":"","cabins_total":"","cabins":"","crew":"160","hull_configuration":"","hull_material":"Steel","superstructure":"","deck_material":"Teak","decks_nb":"","quantity":"3","fuel_type":"Coal","manufacturer":"Parsons","eng_model":"","power":"6500hp / 4100kW","total_power":"19500hp / 12300kW","propulsion":"Triple Screw","max_speed":"16.00 kts","cruising_speed":"13.00 kts","range":"","fuel_capacity":"","water_capacity":"","generator":"","stabilizers":"","thrusters":"","amenities":""}
{"name":"Azzam","type":"Motor Yacht","yac_model":"Custom","sub_type":"","builder":"Lurssen Yachts","naval_architect":"Lurssen Yachts","exterior_designers":"Nauta Design","interior_designer":"Christophe Leoni","year":"2013","flag":"","mca":"","class_":"","hull_nb":"","hull_colour":"","length_overall":"180.60m (592'6\"ft)","length_at_waterline":"","beam":"20.80m (68'2\"ft)","draft_min":"","draft_max":"4.30m (14'1\"ft)","gross_tonnage":"","guests":"","cabins_total":"","cabins":"","crew":"","hull_configuration":"","hull_material":"Steel","superstructure":"","deck_material":"","decks_nb":"","quantity":"2","fuel_type":"Gas Turbine","manufacturer":"","eng_model":"","power":"23500hp / 17524kW","total_power":"94000hp / 70096kW","propulsion":"","max_speed":"30.00 kts","cruising_speed":"","range":"","fuel_capacity":"","water_capacity":"","generator":"","stabilizers":"","thrusters":"","amenities":""}
{"name":"Dilbar","type":"Motor Yacht","yac_model":"Custom","sub_type":"","builder":"Lurssen Yachts","naval_architect":"Lurssen Yachts","exterior_designers":"Espen Oeino","interior_designer":"Winch Design","year":"2016","flag":"","mca":"","class_":"Lloyds","hull_nb":"","hull_colour":"","length_overall":"156.00m (511'9\"ft)","length_at_waterline":"","beam":"","draft_min":"","draft_max":"","gross_tonnage":"","guests":"","cabins_total":"","cabins":"","crew":"","hull_configuration":"Displacement","hull_material":"Steel","superstructure":"Aluminium","deck_material":"Teak","decks_nb":"","quantity":"2","fuel_type":"Gas Turbine","manufacturer":"","eng_model":"","power":"23500hp / 17524kW","total_power":"- / -","propulsion":"","max_speed":"","cruising_speed":"","range":"","fuel_capacity":"","water_capacity":"","generator":"","stabilizers":"","thrusters":"","amenities":""}
{"name":"Al Mirqab","type":"Motor Yacht","yac_model":"Custom","sub_type":"","builder":"Kusch Yachts","naval_architect":"Kusch Yachts","exterior_designers":"Tim Heywood Design","interior_designer":"Winch Design","year":"2008","flag":"Cayman Islands","mca":"","class_":"LR","hull_nb":"681","hull_colour":"","length_overall":"133.00m (436'4\"ft)","length_at_waterline":"","beam":"20.00m (65'7\"ft)","draft_min":"","draft_max":"4.90m (16'0\"ft)","gross_tonnage":"5000 tonnes","guests":"60","cabins_total":"","cabins":"","crew":"60","hull_configuration":"Displacement","hull_material":"Steel","superstructure":"Aluminium","deck_material":"Teak","decks_nb":"","quantity":"2","fuel_type":"Diesel-Electric","manufacturer":"","eng_model":"","power":"6700hp / 5000kW","total_power":"13400hp / 10000kW","propulsion":"Twin Screw","max_speed":"23.00 kts","cruising_speed":"21.00 kts","range":"","fuel_capacity":"","water_capacity":"","generator":"5 x - 345 kW","stabilizers":"","thrusters":"","amenities":""}
{"name":"Fulk Al Salamah","type":"Motor Yacht","yac_model":"Custom","sub_type":"","builder":"Mariotti Yachts","naval_architect":"Mariotti Yachts","exterior_designers":"Studio de Jorio","interior_designer":"","year":"2016","flag":"","mca":"","class_":"","hull_nb":"131","hull_colour":"","length_overall":"164.00m (538'0\"ft)","length_at_waterline":"","beam":"","draft_min":"","draft_max":"","gross_tonnage":"","guests":"","cabins_total":"","cabins":"","crew":"","hull_configuration":"Displacement","hull_material":"Steel","superstructure":"Steel / Aluminium","deck_material":"Aluminium & Teak","decks_nb":"","quantity":"2","fuel_type":"Diesel-Electric","manufacturer":"","eng_model":"","power":"6700hp / 5000kW","total_power":"- / -","propulsion":"","max_speed":"","cruising_speed":"","range":"","fuel_capacity":"","water_capacity":"","generator":"","stabilizers":"","thrusters":"","amenities":""}
{"name":"Al Salamah","type":"Motor Yacht","yac_model":"Custom","sub_type":"","builder":"Lurssen Yachts","naval_architect":"Lurssen Yachts","exterior_designers":"Terence Disdale","interior_designer":"Terence Disdale","year":"1999 / 2009","flag":"Saudi Arabia","mca":"","class_":"GL","hull_nb":"13590","hull_colour":"","length_overall":"139.00m (456'0\"ft)","length_at_waterline":"","beam":"23.50m (77'1\"ft)","draft_min":"","draft_max":"4.80m (15'8\"ft)","gross_tonnage":"","guests":"40","cabins_total":"","cabins":"","crew":"96","hull_configuration":"","hull_material":"Steel","superstructure":"Aluminium","deck_material":"Teak","decks_nb":"","quantity":"2","fuel_type":"Diesel","manufacturer":"","eng_model":"","power":"8770hp / 6500kW","total_power":"17540hp / 13000kW","propulsion":"Twin Screw","max_speed":"22.00 kts","cruising_speed":"17.00 kts","range":"0.00 miles at 21 kts","fuel_capacity":"840,000.00 L / 184,773.96 USG","water_capacity":"","generator":"","stabilizers":"","thrusters":"","amenities":""}
{"name":"Prince Abdulaziz","type":"Motor Yacht","yac_model":"Custom","sub_type":"","builder":"Helsingor Vaerft","naval_architect":"Maierform Maritime Technology","exterior_designers":"Maierform Maritime Technology","interior_designer":"David Hicks","year":"1984 / 2005","flag":"Jeddah","mca":"","class_":"LR","hull_nb":"424","hull_colour":"","length_overall":"147.00m (482'3\"ft)","length_at_waterline":"131.43m (431'2\"ft)","beam":"18.30m (60'0\"ft)","draft_min":"","draft_max":"4.88m (16'0\"ft)","gross_tonnage":"4620 tonnes","guests":"64","cabins_total":"","cabins":"","crew":"65","hull_configuration":"","hull_material":"Steel","superstructure":"Steel","deck_material":"Teak","decks_nb":"","quantity":"2","fuel_type":"Diesel","manufacturer":"Semt-Pielstick","eng_model":"12PC2-5-V400","power":"7800hp / 5740kW","total_power":"15600hp / 11480kW","propulsion":"Twin Screw","max_speed":"22.00 kts","cruising_speed":"182.00 kts","range":"500.00 miles at 18 kts","fuel_capacity":"","water_capacity":"","generator":"","stabilizers":"Vickers","thrusters":"","amenities":""}
{"name":"Sailing Yacht A","type":"Sail Yacht","yac_model":"Custom","sub_type":"Motor Sailer","builder":"Nobiskrug","naval_architect":"Nobiskrug","exterior_designers":"Philippe Starck","interior_designer":"Philippe Starck","year":"2017","flag":"Bermuda","mca":"","class_":"Lloyds Register","hull_nb":"787","hull_colour":"","length_overall":"142.80m (468'6\"ft)","length_at_waterline":"","beam":"24.90m (81'8\"ft)","draft_min":"","draft_max":"8.00m (26'2\"ft)","gross_tonnage":"12700 tonnes","guests":"","cabins_total":"","cabins":"","crew":"","hull_configuration":"","hull_material":"Steel","superstructure":"Composite","deck_material":"Teak","decks_nb":"","quantity":"2","fuel_type":"Diesel","manufacturer":"Semt-Pielstick","eng_model":"12PC2-5-V400","power":"7800hp / 5740kW","total_power":"- / -","propulsion":"","max_speed":"21.00 kts","cruising_speed":"16.00 kts","range":"","fuel_capacity":"","water_capacity":"","generator":"","stabilizers":"","thrusters":"","amenities":""}
{"name":"Rising Sun","type":"Motor Yacht","yac_model":"Custom","sub_type":"","builder":"Lurssen Yachts","naval_architect":"Lurssen Yachts","exterior_designers":"Jon Bannenberg","interior_designer":"Seccombe Design","year":"2004 / 2007","flag":"Cayman Islands","mca":"","class_":"LR","hull_nb":"13623","hull_colour":"","length_overall":"138.40m (454'0\"ft)","length_at_waterline":"","beam":"18.50m (60'8\"ft)","draft_min":"","draft_max":"5.00m (16'4\"ft)","gross_tonnage":"","guests":"16","cabins_total":"","cabins":"","crew":"45","hull_configuration":"","hull_material":"Steel","superstructure":"Aluminium","deck_material":"Teak","decks_nb":"","quantity":"4","fuel_type":"Diesel","manufacturer":"MTU","eng_model":"20V 8000 M90","power":"12230hp / 9000kW","total_power":"48920hp / 36000kW","propulsion":"Quadruple Screw","max_speed":"28.00 kts","cruising_speed":"26.00 kts","range":"","fuel_capacity":"","water_capacity":"","generator":"","stabilizers":"","thrusters":"","amenities":""}
{"name":"Topaz","type":"Motor Yacht","yac_model":"Custom","sub_type":"","builder":"Lurssen Yachts","naval_architect":"Lurssen Yachts","exterior_designers":"Tim Heywood Design","interior_designer":"Terence Disdale","year":"2012","flag":"","mca":"","class_":"Lloyds Register","hull_nb":"13677","hull_colour":"","length_overall":"147.25m (483'1\"ft)","length_at_waterline":"","beam":"21.50m (70'6\"ft)","draft_min":"","draft_max":"","gross_tonnage":"11589 tonnes","guests":"","cabins_total":"","cabins":"","crew":"","hull_configuration":"Displacement","hull_material":"Steel","superstructure":"Aluminium","deck_material":"","decks_nb":"","quantity":"4","fuel_type":"Diesel","manufacturer":"MTU","eng_model":"20V 8000 M90","power":"12230hp / 9000kW","total_power":"- / -","propulsion":"","max_speed":"","cruising_speed":"","range":"","fuel_capacity":"","water_capacity":"","generator":"","stabilizers":"","thrusters":"","amenities":""}
{"name":"Serene","type":"Motor Yacht","yac_model":"Custom","sub_type":"","builder":"Fincantieri Yachts","naval_architect":"Espen Oeino","exterior_designers":"Espen Oeino","interior_designer":"Reymond Langton Design","year":"2011","flag":"","mca":"","class_":"Lloyds Register, SOLAS","hull_nb":"6154","hull_colour":"","length_overall":"133.90m (439'3\"ft)","length_at_waterline":"","beam":"18.50m (60'8\"ft)","draft_min":"","draft_max":"5.50m (18'0\"ft)","gross_tonnage":"8230 tonnes","guests":"24","cabins_total":"12","cabins":"","crew":"52","hull_configuration":"","hull_material":"Steel","superstructure":"","deck_material":"","decks_nb":"7","quantity":"4","fuel_type":"Diesel","manufacturer":"MTU","eng_model":"20V 8000 M90","power":"12230hp / 9000kW","total_power":"- / -","propulsion":"Twin Screw","max_speed":"","cruising_speed":"15.00 kts","range":"","fuel_capacity":"","water_capacity":"","generator":"","stabilizers":"4 fins Zero Speed","thrusters":"Two forward, two aft","amenities":""}
